aldryn_jobs/__init__.py
aldryn_jobs/admin.py
aldryn_jobs/apps.py
aldryn_jobs/cms_appconfig.py
aldryn_jobs/cms_apps.py
aldryn_jobs/cms_menus.py
aldryn_jobs/cms_plugins.py
aldryn_jobs/cms_toolbars.py
aldryn_jobs/cms_wizards.py
aldryn_jobs/forms.py
aldryn_jobs/managers.py
aldryn_jobs/models.py
aldryn_jobs/search_indexes.py
aldryn_jobs/urls.py
aldryn_jobs/utils.py
aldryn_jobs/views.py
aldryn_jobs/boilerplates/bootstrap3/templates/aldryn_jobs/base.html
aldryn_jobs/boilerplates/bootstrap3/templates/aldryn_jobs/fullwidth.html
aldryn_jobs/boilerplates/bootstrap3/templates/aldryn_jobs/jobs_detail.html
aldryn_jobs/boilerplates/bootstrap3/templates/aldryn_jobs/jobs_list.html
aldryn_jobs/boilerplates/bootstrap3/templates/aldryn_jobs/two_column.html
aldryn_jobs/boilerplates/bootstrap3/templates/aldryn_jobs/emails/confirmation.body.html
aldryn_jobs/boilerplates/bootstrap3/templates/aldryn_jobs/emails/confirmation.body.txt
aldryn_jobs/boilerplates/bootstrap3/templates/aldryn_jobs/emails/confirmation.subject.txt
aldryn_jobs/boilerplates/bootstrap3/templates/aldryn_jobs/emails/notification.body.html
aldryn_jobs/boilerplates/bootstrap3/templates/aldryn_jobs/emails/notification.body.txt
aldryn_jobs/boilerplates/bootstrap3/templates/aldryn_jobs/emails/notification.subject.txt
aldryn_jobs/boilerplates/bootstrap3/templates/aldryn_jobs/emails/rejection_letter.body.html
aldryn_jobs/boilerplates/bootstrap3/templates/aldryn_jobs/emails/rejection_letter.body.txt
aldryn_jobs/boilerplates/bootstrap3/templates/aldryn_jobs/emails/rejection_letter.subject.txt
aldryn_jobs/boilerplates/bootstrap3/templates/aldryn_jobs/includes/application.html
aldryn_jobs/boilerplates/bootstrap3/templates/aldryn_jobs/includes/job.html
aldryn_jobs/boilerplates/bootstrap3/templates/aldryn_jobs/plugins/categories_list.html
aldryn_jobs/boilerplates/bootstrap3/templates/aldryn_jobs/plugins/latest_entries.html
aldryn_jobs/boilerplates/legacy/templates/aldryn_jobs/base.html
aldryn_jobs-3.0.0.dist-info/DESCRIPTION.rst
aldryn_jobs-3.0.0.dist-info/METADATA
aldryn_jobs-3.0.0.dist-info/RECORD
aldryn_jobs-3.0.0.dist-info/WHEEL
aldryn_jobs-3.0.0.dist-info/metadata.json
aldryn_jobs-3.0.0.dist-info/top_level.txt
