Metadata-Version: 2.0
Name: aldryn-jobs
Version: 3.0.0
Summary: Publish job openings on your site
Home-page: https://github.com/aldryn/aldryn-jobs
Author: Divio AG
Author-email: info@divio.ch
License: LICENSE.txt
Platform: OS Independent
Classifier: Development Status :: 5 - Production/Stable
Classifier: Environment :: Web Environment
Classifier: Framework :: Django
Classifier: Framework :: Django :: 1.8
Classifier: Framework :: Django :: 1.9
Classifier: Framework :: Django :: 1.10
Classifier: Framework :: Django :: 1.11
Classifier: Intended Audience :: Developers
Classifier: License :: OSI Approved :: BSD License
Classifier: Operating System :: OS Independent
Classifier: Programming Language :: Python
Classifier: Programming Language :: Python :: 2.7
Classifier: Programming Language :: Python :: 3.4
Classifier: Programming Language :: Python :: 3.5
Classifier: Programming Language :: Python :: 3.6
Classifier: Topic :: Internet :: WWW/HTTP :: Dynamic Content
Classifier: Topic :: Software Development
Classifier: Topic :: Software Development :: Libraries :: Application Frameworks
Requires-Dist: Django (>=1.8,<2.0)
Requires-Dist: aldryn-apphooks-config (>=0.4.0)
Requires-Dist: aldryn-boilerplates
Requires-Dist: aldryn-categories
Requires-Dist: aldryn-common (>=0.1.3)
Requires-Dist: aldryn-translation-tools (>=0.2.1)
Requires-Dist: cssutils
Requires-Dist: django-admin-sortable2 (>=0.5.2)
Requires-Dist: django-appdata (>=0.1.4)
Requires-Dist: django-bootstrap3
Requires-Dist: django-cms (>=3.4)
Requires-Dist: django-emailit
Requires-Dist: django-multiupload (>=0.5.1)
Requires-Dist: django-parler
Requires-Dist: django-sortedm2m (>=1.2.2)
Requires-Dist: django-standard-form
Requires-Dist: djangocms-text-ckeditor (>=1.0.10)
Requires-Dist: html5lib (<=0.9999999)
Requires-Dist: lxml
Requires-Dist: pytz
